{
  "type": "Program",
  "body": [
    {
      "type": "ExpressionStatement",
      "expression": {
        "type": "Literal",
        "value": "use strict"
      }
    },
    {
      "type": "VariableDeclaration",
      "declarations": [
        {
          "type": "VariableDeclarator",
          "id": {
            "type": "Identifier",
            "name": "assert"
          },
          "init": {
            "type": "CallExpression",
            "callee": {
              "type": "Identifier",
              "name": "require"
            },
            "arguments": [
              {
                "type": "Literal",
                "value": "assert"
              }
            ]
          }
        },
        {
          "type": "VariableDeclarator",
          "id": {
            "type": "Identifier",
            "name": "Keygrip"
          },
          "init": {
            "type": "CallExpression",
            "callee": {
              "type": "Identifier",
              "name": "require"
            },
            "arguments": [
              {
                "type": "Literal",
                "value": "./"
              }
            ]
          }
        },
        {
          "type": "VariableDeclarator",
          "id": {
            "type": "Identifier",
            "name": "keylist"
          },
          "init": null
        },
        {
          "type": "VariableDeclarator",
          "id": {
            "type": "Identifier",
            "name": "keys"
          },
          "init": null
        },
        {
          "type": "VariableDeclarator",
          "id": {
            "type": "Identifier",
            "name": "hash"
          },
          "init": null
        },
        {
          "type": "VariableDeclarator",
          "id": {
            "type": "Identifier",
            "name": "index"
          },
          "init": null
        }
      ],
      "kind": "var"
    },
    {
      "type": "ExpressionStatement",
      "expression": {
        "type": "CallExpression",
        "callee": {
          "type": "MemberExpression",
          "computed": false,
          "object": {
            "type": "Identifier",
            "name": "assert"
          },
          "property": {
            "type": "Identifier",
            "name": "throws"
          }
        },
        "arguments": [
          {
            "type": "FunctionExpression",
            "id": null,
            "params": [],
            "defaults": [],
            "body": {
              "type": "BlockStatement",
              "body": [
                {
                  "type": "ExpressionStatement",
                  "expression": {
                    "type": "AssignmentExpression",
                    "operator": "=",
                    "left": {
                      "type": "Identifier",
                      "name": "keys"
                    },
                    "right": {
                      "type": "NewExpression",
                      "callee": {
                        "type": "Identifier",
                        "name": "Keygrip"
                      },
                      "arguments": []
                    }
                  }
                }
              ]
            },
            "rest": null,
            "generator": false,
            "expression": false
          },
          {
            "type": "Literal",
            "value": {}
          }
        ]
      }
    },
    {
      "type": "ExpressionStatement",
      "expression": {
        "type": "AssignmentExpression",
        "operator": "=",
        "left": {
          "type": "Identifier",
          "name": "keys"
        },
        "right": {
          "type": "NewExpression",
          "callee": {
            "type": "Identifier",
            "name": "Keygrip"
          },
          "arguments": [
            {
              "type": "ArrayExpression",
              "elements": [
                {
                  "type": "Literal",
                  "value": "06ae66fdc6c2faf5a401b70e0bf885cb"
                }
              ]
            }
          ]
        }
      }
    },
    {
      "type": "ExpressionStatement",
      "expression": {
        "type": "AssignmentExpression",
        "operator": "=",
        "left": {
          "type": "Identifier",
          "name": "hash"
        },
        "right": {
          "type": "CallExpression",
          "callee": {
            "type": "MemberExpression",
            "computed": false,
            "object": {
              "type": "Identifier",
              "name": "keys"
            },
            "property": {
              "type": "Identifier",
              "name": "sign"
            }
          },
          "arguments": [
            {
              "type": "Literal",
              "value": "bieberschnitzel"
            }
          ]
        }
      }
    },
    {
      "type": "ExpressionStatement",
      "expression": {
        "type": "CallExpression",
        "callee": {
          "type": "MemberExpression",
          "computed": false,
          "object": {
            "type": "Identifier",
            "name": "assert"
          },
          "property": {
            "type": "Identifier",
            "name": "ok"
          }
        },
        "arguments": [
          {
            "type": "CallExpression",
            "callee": {
              "type": "MemberExpression",
              "computed": false,
              "object": {
                "type": "Literal",
                "value": {}
              },
              "property": {
                "type": "Identifier",
                "name": "test"
              }
            },
            "arguments": [
              {
                "type": "Identifier",
                "name": "hash"
              }
            ]
          }
        ]
      }
    },
    {
      "type": "ExpressionStatement",
      "expression": {
        "type": "AssignmentExpression",
        "operator": "=",
        "left": {
          "type": "Identifier",
          "name": "keylist"
        },
        "right": {
          "type": "ArrayExpression",
          "elements": [
            {
              "type": "Literal",
              "value": "SEKRIT3"
            },
            {
              "type": "Literal",
              "value": "SEKRIT2"
            },
            {
              "type": "Literal",
              "value": "SEKRIT1"
            }
          ]
        }
      }
    },
    {
      "type": "ExpressionStatement",
      "expression": {
        "type": "AssignmentExpression",
        "operator": "=",
        "left": {
          "type": "Identifier",
          "name": "keys"
        },
        "right": {
          "type": "CallExpression",
          "callee": {
            "type": "Identifier",
            "name": "Keygrip"
          },
          "arguments": [
            {
              "type": "Identifier",
              "name": "keylist"
            }
          ]
        }
      }
    },
    {
      "type": "ExpressionStatement",
      "expression": {
        "type": "CallExpression",
        "callee": {
          "type": "Identifier",
          "name": "testKeygripInstance"
        },
        "arguments": [
          {
            "type": "Identifier",
            "name": "keys"
          }
        ]
      }
    },
    {
      "type": "ExpressionStatement",
      "expression": {
        "type": "AssignmentExpression",
        "operator": "=",
        "left": {
          "type": "Identifier",
          "name": "keylist"
        },
        "right": {
          "type": "ArrayExpression",
          "elements": [
            {
              "type": "Literal",
              "value": "Newest"
            },
            {
              "type": "Literal",
              "value": "AnotherKey"
            },
            {
              "type": "Literal",
              "value": "Oldest"
            }
          ]
        }
      }
    },
    {
      "type": "ExpressionStatement",
      "expression": {
        "type": "AssignmentExpression",
        "operator": "=",
        "left": {
          "type": "Identifier",
          "name": "keys"
        },
        "right": {
          "type": "CallExpression",
          "callee": {
            "type": "Identifier",
            "name": "Keygrip"
          },
          "arguments": [
            {
              "type": "Identifier",
              "name": "keylist"
            },
            {
              "type": "Literal",
              "value": "sha256"
            },
            {
              "type": "Literal",
              "value": "hex"
            }
          ]
        }
      }
    },
    {
      "type": "ExpressionStatement",
      "expression": {
        "type": "CallExpression",
        "callee": {
          "type": "Identifier",
          "name": "testKeygripInstance"
        },
        "arguments": [
          {
            "type": "Identifier",
            "name": "keys"
          }
        ]
      }
    },
    {
      "type": "FunctionDeclaration",
      "id": {
        "type": "Identifier",
        "name": "testKeygripInstance"
      },
      "params": [
        {
          "type": "Identifier",
          "name": "keys"
        }
      ],
      "defaults": [],
      "body": {
        "type": "BlockStatement",
        "body": [
          {
            "type": "ExpressionStatement",
            "expression": {
              "type": "AssignmentExpression",
              "operator": "=",
              "left": {
                "type": "Identifier",
                "name": "hash"
              },
              "right": {
                "type": "CallExpression",
                "callee": {
                  "type": "MemberExpression",
                  "computed": false,
                  "object": {
                    "type": "Identifier",
                    "name": "keys"
                  },
                  "property": {
                    "type": "Identifier",
                    "name": "sign"
                  }
                },
                "arguments": [
                  {
                    "type": "Literal",
                    "value": "bieberschnitzel"
                  }
                ]
              }
            }
          },
          {
            "type": "ExpressionStatement",
            "expression": {
              "type": "AssignmentExpression",
              "operator": "=",
              "left": {
                "type": "Identifier",
                "name": "index"
              },
              "right": {
                "type": "CallExpression",
                "callee": {
                  "type": "MemberExpression",
                  "computed": false,
                  "object": {
                    "type": "Identifier",
                    "name": "keys"
                  },
                  "property": {
                    "type": "Identifier",
                    "name": "index"
                  }
                },
                "arguments": [
                  {
                    "type": "Literal",
                    "value": "bieberschnitzel"
                  },
                  {
                    "type": "Identifier",
                    "name": "hash"
                  }
                ]
              }
            }
          },
          {
            "type": "ExpressionStatement",
            "expression": {
              "type": "CallExpression",
              "callee": {
                "type": "MemberExpression",
                "computed": false,
                "object": {
                  "type": "Identifier",
                  "name": "assert"
                },
                "property": {
                  "type": "Identifier",
                  "name": "equal"
                }
              },
              "arguments": [
                {
                  "type": "Identifier",
                  "name": "index"
                },
                {
                  "type": "Literal",
                  "value": 0
                }
              ]
            }
          },
          {
            "type": "VariableDeclaration",
            "declarations": [
              {
                "type": "VariableDeclarator",
                "id": {
                  "type": "Identifier",
                  "name": "matched"
                },
                "init": {
                  "type": "CallExpression",
                  "callee": {
                    "type": "MemberExpression",
                    "computed": false,
                    "object": {
                      "type": "Identifier",
                      "name": "keys"
                    },
                    "property": {
                      "type": "Identifier",
                      "name": "verify"
                    }
                  },
                  "arguments": [
                    {
                      "type": "Literal",
                      "value": "bieberschnitzel"
                    },
                    {
                      "type": "Identifier",
                      "name": "hash"
                    }
                  ]
                }
              }
            ],
            "kind": "var"
          },
          {
            "type": "ExpressionStatement",
            "expression": {
              "type": "CallExpression",
              "callee": {
                "type": "MemberExpression",
                "computed": false,
                "object": {
                  "type": "Identifier",
                  "name": "assert"
                },
                "property": {
                  "type": "Identifier",
                  "name": "ok"
                }
              },
              "arguments": [
                {
                  "type": "Identifier",
                  "name": "matched"
                }
              ]
            }
          },
          {
            "type": "ExpressionStatement",
            "expression": {
              "type": "AssignmentExpression",
              "operator": "=",
              "left": {
                "type": "Identifier",
                "name": "index"
              },
              "right": {
                "type": "CallExpression",
                "callee": {
                  "type": "MemberExpression",
                  "computed": false,
                  "object": {
                    "type": "Identifier",
                    "name": "keys"
                  },
                  "property": {
                    "type": "Identifier",
                    "name": "index"
                  }
                },
                "arguments": [
                  {
                    "type": "Literal",
                    "value": "bieberschnitzel"
                  },
                  {
                    "type": "Literal",
                    "value": "o_O"
                  }
                ]
              }
            }
          },
          {
            "type": "ExpressionStatement",
            "expression": {
              "type": "CallExpression",
              "callee": {
                "type": "MemberExpression",
                "computed": false,
                "object": {
                  "type": "Identifier",
                  "name": "assert"
                },
                "property": {
                  "type": "Identifier",
                  "name": "equal"
                }
              },
              "arguments": [
                {
                  "type": "Identifier",
                  "name": "index"
                },
                {
                  "type": "UnaryExpression",
                  "operator": "-",
                  "argument": {
                    "type": "Literal",
                    "value": 1
                  },
                  "prefix": true
                }
              ]
            }
          },
          {
            "type": "ExpressionStatement",
            "expression": {
              "type": "CallExpression",
              "callee": {
                "type": "MemberExpression",
                "computed": false,
                "object": {
                  "type": "Identifier",
                  "name": "keylist"
                },
                "property": {
                  "type": "Identifier",
                  "name": "unshift"
                }
              },
              "arguments": [
                {
                  "type": "Literal",
                  "value": "SEKRIT4"
                }
              ]
            }
          },
          {
            "type": "ExpressionStatement",
            "expression": {
              "type": "CallExpression",
              "callee": {
                "type": "MemberExpression",
                "computed": false,
                "object": {
                  "type": "Identifier",
                  "name": "keylist"
                },
                "property": {
                  "type": "Identifier",
                  "name": "pop"
                }
              },
              "arguments": []
            }
          },
          {
            "type": "ExpressionStatement",
            "expression": {
              "type": "AssignmentExpression",
              "operator": "=",
              "left": {
                "type": "Identifier",
                "name": "index"
              },
              "right": {
                "type": "CallExpression",
                "callee": {
                  "type": "MemberExpression",
                  "computed": false,
                  "object": {
                    "type": "Identifier",
                    "name": "keys"
                  },
                  "property": {
                    "type": "Identifier",
                    "name": "index"
                  }
                },
                "arguments": [
                  {
                    "type": "Literal",
                    "value": "bieberschnitzel"
                  },
                  {
                    "type": "Identifier",
                    "name": "hash"
                  }
                ]
              }
            }
          },
          {
            "type": "ExpressionStatement",
            "expression": {
              "type": "CallExpression",
              "callee": {
                "type": "MemberExpression",
                "computed": false,
                "object": {
                  "type": "Identifier",
                  "name": "assert"
                },
                "property": {
                  "type": "Identifier",
                  "name": "equal"
                }
              },
              "arguments": [
                {
                  "type": "Identifier",
                  "name": "index"
                },
                {
                  "type": "Literal",
                  "value": 1
                }
              ]
            }
          },
          {
            "type": "ExpressionStatement",
            "expression": {
              "type": "AssignmentExpression",
              "operator": "=",
              "left": {
                "type": "Identifier",
                "name": "hash"
              },
              "right": {
                "type": "CallExpression",
                "callee": {
                  "type": "MemberExpression",
                  "computed": false,
                  "object": {
                    "type": "Identifier",
                    "name": "keys"
                  },
                  "property": {
                    "type": "Identifier",
                    "name": "sign"
                  }
                },
                "arguments": [
                  {
                    "type": "Literal",
                    "value": "bieberschnitzel"
                  }
                ]
              }
            }
          }
        ]
      },
      "rest": null,
      "generator": false,
      "expression": false
    }
  ]
}