{
  "type": "Program",
  "body": [
    {
      "type": "VariableDeclaration",
      "declarations": [
        {
          "type": "VariableDeclarator",
          "id": {
            "type": "Identifier",
            "name": "providers_large"
          },
          "init": {
            "type": "ObjectExpression",
            "properties": [
              {
                "type": "Property",
                "key": {
                  "type": "Identifier",
                  "name": "yandex"
                },
                "value": {
                  "type": "ObjectExpression",
                  "properties": [
                    {
                      "type": "Property",
                      "key": {
                        "type": "Identifier",
                        "name": "name"
                      },
                      "value": {
                        "type": "Literal",
                        "value": "Яндекс"
                      },
                      "kind": "init"
                    },
                    {
                      "type": "Property",
                      "key": {
                        "type": "Identifier",
                        "name": "url"
                      },
                      "value": {
                        "type": "Literal",
                        "value": "http://openid.yandex.ru"
                      },
                      "kind": "init"
                    }
                  ]
                },
                "kind": "init"
              },
              {
                "type": "Property",
                "key": {
                  "type": "Identifier",
                  "name": "rambler"
                },
                "value": {
                  "type": "ObjectExpression",
                  "properties": [
                    {
                      "type": "Property",
                      "key": {
                        "type": "Identifier",
                        "name": "name"
                      },
                      "value": {
                        "type": "Literal",
                        "value": "Рамблер"
                      },
                      "kind": "init"
                    },
                    {
                      "type": "Property",
                      "key": {
                        "type": "Identifier",
                        "name": "url"
                      },
                      "value": {
                        "type": "Literal",
                        "value": "http://www.rambler.ru"
                      },
                      "kind": "init"
                    }
                  ]
                },
                "kind": "init"
              },
              {
                "type": "Property",
                "key": {
                  "type": "Identifier",
                  "name": "google"
                },
                "value": {
                  "type": "ObjectExpression",
                  "properties": [
                    {
                      "type": "Property",
                      "key": {
                        "type": "Identifier",
                        "name": "name"
                      },
                      "value": {
                        "type": "Literal",
                        "value": "Google"
                      },
                      "kind": "init"
                    },
                    {
                      "type": "Property",
                      "key": {
                        "type": "Identifier",
                        "name": "url"
                      },
                      "value": {
                        "type": "Literal",
                        "value": "https://www.google.com/accounts/o8/id"
                      },
                      "kind": "init"
                    }
                  ]
                },
                "kind": "init"
              },
              {
                "type": "Property",
                "key": {
                  "type": "Identifier",
                  "name": "yahoo"
                },
                "value": {
                  "type": "ObjectExpression",
                  "properties": [
                    {
                      "type": "Property",
                      "key": {
                        "type": "Identifier",
                        "name": "name"
                      },
                      "value": {
                        "type": "Literal",
                        "value": "Yahoo"
                      },
                      "kind": "init"
                    },
                    {
                      "type": "Property",
                      "key": {
                        "type": "Identifier",
                        "name": "url"
                      },
                      "value": {
                        "type": "Literal",
                        "value": "http://me.yahoo.com/"
                      },
                      "kind": "init"
                    }
                  ]
                },
                "kind": "init"
              },
              {
                "type": "Property",
                "key": {
                  "type": "Identifier",
                  "name": "myopenid"
                },
                "value": {
                  "type": "ObjectExpression",
                  "properties": [
                    {
                      "type": "Property",
                      "key": {
                        "type": "Identifier",
                        "name": "name"
                      },
                      "value": {
                        "type": "Literal",
                        "value": "MyOpenID"
                      },
                      "kind": "init"
                    },
                    {
                      "type": "Property",
                      "key": {
                        "type": "Identifier",
                        "name": "label"
                      },
                      "value": {
                        "type": "Literal",
                        "value": "Введите ваше имя пользователя на MyOpenID."
                      },
                      "kind": "init"
                    },
                    {
                      "type": "Property",
                      "key": {
                        "type": "Identifier",
                        "name": "url"
                      },
                      "value": {
                        "type": "Literal",
                        "value": "http://{username}.myopenid.com/"
                      },
                      "kind": "init"
                    }
                  ]
                },
                "kind": "init"
              }
            ]
          }
        }
      ],
      "kind": "var"
    },
    {
      "type": "VariableDeclaration",
      "declarations": [
        {
          "type": "VariableDeclarator",
          "id": {
            "type": "Identifier",
            "name": "providers_small"
          },
          "init": {
            "type": "ObjectExpression",
            "properties": [
              {
                "type": "Property",
                "key": {
                  "type": "Identifier",
                  "name": "openid"
                },
                "value": {
                  "type": "ObjectExpression",
                  "properties": [
                    {
                      "type": "Property",
                      "key": {
                        "type": "Identifier",
                        "name": "name"
                      },
                      "value": {
                        "type": "Literal",
                        "value": "OpenID"
                      },
                      "kind": "init"
                    },
                    {
                      "type": "Property",
                      "key": {
                        "type": "Identifier",
                        "name": "label"
                      },
                      "value": {
                        "type": "Literal",
                        "value": "Введите ваш OpenID."
                      },
                      "kind": "init"
                    },
                    {
                      "type": "Property",
                      "key": {
                        "type": "Identifier",
                        "name": "url"
                      },
                      "value": {
                        "type": "Literal",
                        "value": null
                      },
                      "kind": "init"
                    }
                  ]
                },
                "kind": "init"
              },
              {
                "type": "Property",
                "key": {
                  "type": "Identifier",
                  "name": "livejournal"
                },
                "value": {
                  "type": "ObjectExpression",
                  "properties": [
                    {
                      "type": "Property",
                      "key": {
                        "type": "Identifier",
                        "name": "name"
                      },
                      "value": {
                        "type": "Literal",
                        "value": "Живой Журнал"
                      },
                      "kind": "init"
                    },
                    {
                      "type": "Property",
                      "key": {
                        "type": "Identifier",
                        "name": "label"
                      },
                      "value": {
                        "type": "Literal",
                        "value": "Введите ваше имя в Живом Журнале."
                      },
                      "kind": "init"
                    },
                    {
                      "type": "Property",
                      "key": {
                        "type": "Identifier",
                        "name": "url"
                      },
                      "value": {
                        "type": "Literal",
                        "value": "http://{username}.livejournal.com/"
                      },
                      "kind": "init"
                    }
                  ]
                },
                "kind": "init"
              },
              {
                "type": "Property",
                "key": {
                  "type": "Identifier",
                  "name": "flickr"
                },
                "value": {
                  "type": "ObjectExpression",
                  "properties": [
                    {
                      "type": "Property",
                      "key": {
                        "type": "Identifier",
                        "name": "name"
                      },
                      "value": {
                        "type": "Literal",
                        "value": "Flickr"
                      },
                      "kind": "init"
                    },
                    {
                      "type": "Property",
                      "key": {
                        "type": "Identifier",
                        "name": "label"
                      },
                      "value": {
                        "type": "Literal",
                        "value": "Введите ваше имя на Flickr."
                      },
                      "kind": "init"
                    },
                    {
                      "type": "Property",
                      "key": {
                        "type": "Identifier",
                        "name": "url"
                      },
                      "value": {
                        "type": "Literal",
                        "value": "http://flickr.com/{username}/"
                      },
                      "kind": "init"
                    }
                  ]
                },
                "kind": "init"
              },
              {
                "type": "Property",
                "key": {
                  "type": "Identifier",
                  "name": "wordpress"
                },
                "value": {
                  "type": "ObjectExpression",
                  "properties": [
                    {
                      "type": "Property",
                      "key": {
                        "type": "Identifier",
                        "name": "name"
                      },
                      "value": {
                        "type": "Literal",
                        "value": "Wordpress"
                      },
                      "kind": "init"
                    },
                    {
                      "type": "Property",
                      "key": {
                        "type": "Identifier",
                        "name": "label"
                      },
                      "value": {
                        "type": "Literal",
                        "value": "Введите ваше имя на Wordpress.com."
                      },
                      "kind": "init"
                    },
                    {
                      "type": "Property",
                      "key": {
                        "type": "Identifier",
                        "name": "url"
                      },
                      "value": {
                        "type": "Literal",
                        "value": "http://{username}.wordpress.com/"
                      },
                      "kind": "init"
                    }
                  ]
                },
                "kind": "init"
              },
              {
                "type": "Property",
                "key": {
                  "type": "Identifier",
                  "name": "blogger"
                },
                "value": {
                  "type": "ObjectExpression",
                  "properties": [
                    {
                      "type": "Property",
                      "key": {
                        "type": "Identifier",
                        "name": "name"
                      },
                      "value": {
                        "type": "Literal",
                        "value": "Blogger"
                      },
                      "kind": "init"
                    },
                    {
                      "type": "Property",
                      "key": {
                        "type": "Identifier",
                        "name": "label"
                      },
                      "value": {
                        "type": "Literal",
                        "value": "Ваш Blogger аккаунт"
                      },
                      "kind": "init"
                    },
                    {
                      "type": "Property",
                      "key": {
                        "type": "Identifier",
                        "name": "url"
                      },
                      "value": {
                        "type": "Literal",
                        "value": "http://{username}.blogspot.com/"
                      },
                      "kind": "init"
                    }
                  ]
                },
                "kind": "init"
              },
              {
                "type": "Property",
                "key": {
                  "type": "Identifier",
                  "name": "verisign"
                },
                "value": {
                  "type": "ObjectExpression",
                  "properties": [
                    {
                      "type": "Property",
                      "key": {
                        "type": "Identifier",
                        "name": "name"
                      },
                      "value": {
                        "type": "Literal",
                        "value": "Verisign"
                      },
                      "kind": "init"
                    },
                    {
                      "type": "Property",
                      "key": {
                        "type": "Identifier",
                        "name": "label"
                      },
                      "value": {
                        "type": "Literal",
                        "value": "Ваше имя пользователя на Verisign"
                      },
                      "kind": "init"
                    },
                    {
                      "type": "Property",
                      "key": {
                        "type": "Identifier",
                        "name": "url"
                      },
                      "value": {
                        "type": "Literal",
                        "value": "http://{username}.pip.verisignlabs.com/"
                      },
                      "kind": "init"
                    }
                  ]
                },
                "kind": "init"
              },
              {
                "type": "Property",
                "key": {
                  "type": "Identifier",
                  "name": "google_profile"
                },
                "value": {
                  "type": "ObjectExpression",
                  "properties": [
                    {
                      "type": "Property",
                      "key": {
                        "type": "Identifier",
                        "name": "name"
                      },
                      "value": {
                        "type": "Literal",
                        "value": "Профиль Google"
                      },
                      "kind": "init"
                    },
                    {
                      "type": "Property",
                      "key": {
                        "type": "Identifier",
                        "name": "label"
                      },
                      "value": {
                        "type": "Literal",
                        "value": "Введите ваше имя на Google Profile"
                      },
                      "kind": "init"
                    },
                    {
                      "type": "Property",
                      "key": {
                        "type": "Identifier",
                        "name": "url"
                      },
                      "value": {
                        "type": "Literal",
                        "value": "http://www.google.com/profiles/{username}"
                      },
                      "kind": "init"
                    }
                  ]
                },
                "kind": "init"
              }
            ]
          }
        }
      ],
      "kind": "var"
    },
    {
      "type": "ExpressionStatement",
      "expression": {
        "type": "AssignmentExpression",
        "operator": "=",
        "left": {
          "type": "MemberExpression",
          "computed": false,
          "object": {
            "type": "Identifier",
            "name": "openid"
          },
          "property": {
            "type": "Identifier",
            "name": "locale"
          }
        },
        "right": {
          "type": "Literal",
          "value": "ru"
        }
      }
    },
    {
      "type": "ExpressionStatement",
      "expression": {
        "type": "AssignmentExpression",
        "operator": "=",
        "left": {
          "type": "MemberExpression",
          "computed": false,
          "object": {
            "type": "Identifier",
            "name": "openid"
          },
          "property": {
            "type": "Identifier",
            "name": "sprite"
          }
        },
        "right": {
          "type": "Literal",
          "value": "ru"
        }
      }
    },
    {
      "type": "ExpressionStatement",
      "expression": {
        "type": "AssignmentExpression",
        "operator": "=",
        "left": {
          "type": "MemberExpression",
          "computed": false,
          "object": {
            "type": "Identifier",
            "name": "openid"
          },
          "property": {
            "type": "Identifier",
            "name": "demo_text"
          }
        },
        "right": {
          "type": "Literal",
          "value": "В демонстрационном режиме на клиенте. В действительности произошел бы сабмит следующего OpenID:"
        }
      }
    },
    {
      "type": "ExpressionStatement",
      "expression": {
        "type": "AssignmentExpression",
        "operator": "=",
        "left": {
          "type": "MemberExpression",
          "computed": false,
          "object": {
            "type": "Identifier",
            "name": "openid"
          },
          "property": {
            "type": "Identifier",
            "name": "signin_text"
          }
        },
        "right": {
          "type": "Literal",
          "value": "Войти"
        }
      }
    },
    {
      "type": "ExpressionStatement",
      "expression": {
        "type": "AssignmentExpression",
        "operator": "=",
        "left": {
          "type": "MemberExpression",
          "computed": false,
          "object": {
            "type": "Identifier",
            "name": "openid"
          },
          "property": {
            "type": "Identifier",
            "name": "image_title"
          }
        },
        "right": {
          "type": "Literal",
          "value": "войти c {provider}"
        }
      }
    }
  ]
}