{
  "type": "Program",
  "body": [
    {
      "type": "VariableDeclaration",
      "declarations": [
        {
          "type": "VariableDeclarator",
          "id": {
            "type": "Identifier",
            "name": "common"
          },
          "init": {
            "type": "CallExpression",
            "callee": {
              "type": "Identifier",
              "name": "require"
            },
            "arguments": [
              {
                "type": "Literal",
                "value": "../common"
              }
            ]
          }
        }
      ],
      "kind": "var"
    },
    {
      "type": "VariableDeclaration",
      "declarations": [
        {
          "type": "VariableDeclarator",
          "id": {
            "type": "Identifier",
            "name": "assert"
          },
          "init": {
            "type": "CallExpression",
            "callee": {
              "type": "Identifier",
              "name": "require"
            },
            "arguments": [
              {
                "type": "Literal",
                "value": "assert"
              }
            ]
          }
        }
      ],
      "kind": "var"
    },
    {
      "type": "VariableDeclaration",
      "declarations": [
        {
          "type": "VariableDeclarator",
          "id": {
            "type": "Identifier",
            "name": "tls"
          },
          "init": {
            "type": "CallExpression",
            "callee": {
              "type": "Identifier",
              "name": "require"
            },
            "arguments": [
              {
                "type": "Literal",
                "value": "tls"
              }
            ]
          }
        }
      ],
      "kind": "var"
    },
    {
      "type": "VariableDeclaration",
      "declarations": [
        {
          "type": "VariableDeclarator",
          "id": {
            "type": "Identifier",
            "name": "net"
          },
          "init": {
            "type": "CallExpression",
            "callee": {
              "type": "Identifier",
              "name": "require"
            },
            "arguments": [
              {
                "type": "Literal",
                "value": "net"
              }
            ]
          }
        }
      ],
      "kind": "var"
    },
    {
      "type": "VariableDeclaration",
      "declarations": [
        {
          "type": "VariableDeclarator",
          "id": {
            "type": "Identifier",
            "name": "fs"
          },
          "init": {
            "type": "CallExpression",
            "callee": {
              "type": "Identifier",
              "name": "require"
            },
            "arguments": [
              {
                "type": "Literal",
                "value": "fs"
              }
            ]
          }
        }
      ],
      "kind": "var"
    },
    {
      "type": "VariableDeclaration",
      "declarations": [
        {
          "type": "VariableDeclarator",
          "id": {
            "type": "Identifier",
            "name": "path"
          },
          "init": {
            "type": "CallExpression",
            "callee": {
              "type": "Identifier",
              "name": "require"
            },
            "arguments": [
              {
                "type": "Literal",
                "value": "path"
              }
            ]
          }
        }
      ],
      "kind": "var"
    },
    {
      "type": "VariableDeclaration",
      "declarations": [
        {
          "type": "VariableDeclarator",
          "id": {
            "type": "Identifier",
            "name": "serverConnected"
          },
          "init": {
            "type": "Literal",
            "value": 0
          }
        }
      ],
      "kind": "var"
    },
    {
      "type": "VariableDeclaration",
      "declarations": [
        {
          "type": "VariableDeclarator",
          "id": {
            "type": "Identifier",
            "name": "clientConnected"
          },
          "init": {
            "type": "Literal",
            "value": 0
          }
        }
      ],
      "kind": "var"
    },
    {
      "type": "VariableDeclaration",
      "declarations": [
        {
          "type": "VariableDeclarator",
          "id": {
            "type": "Identifier",
            "name": "options"
          },
          "init": {
            "type": "ObjectExpression",
            "properties": [
              {
                "type": "Property",
                "key": {
                  "type": "Identifier",
                  "name": "key"
                },
                "value": {
                  "type": "CallExpression",
                  "callee": {
                    "type": "MemberExpression",
                    "computed": false,
                    "object": {
                      "type": "Identifier",
                      "name": "fs"
                    },
                    "property": {
                      "type": "Identifier",
                      "name": "readFileSync"
                    }
                  },
                  "arguments": [
                    {
                      "type": "CallExpression",
                      "callee": {
                        "type": "MemberExpression",
                        "computed": false,
                        "object": {
                          "type": "Identifier",
                          "name": "path"
                        },
                        "property": {
                          "type": "Identifier",
                          "name": "join"
                        }
                      },
                      "arguments": [
                        {
                          "type": "MemberExpression",
                          "computed": false,
                          "object": {
                            "type": "Identifier",
                            "name": "common"
                          },
                          "property": {
                            "type": "Identifier",
                            "name": "fixturesDir"
                          }
                        },
                        {
                          "type": "Literal",
                          "value": "test_key.pem"
                        }
                      ]
                    }
                  ]
                },
                "kind": "init"
              },
              {
                "type": "Property",
                "key": {
                  "type": "Identifier",
                  "name": "cert"
                },
                "value": {
                  "type": "CallExpression",
                  "callee": {
                    "type": "MemberExpression",
                    "computed": false,
                    "object": {
                      "type": "Identifier",
                      "name": "fs"
                    },
                    "property": {
                      "type": "Identifier",
                      "name": "readFileSync"
                    }
                  },
                  "arguments": [
                    {
                      "type": "CallExpression",
                      "callee": {
                        "type": "MemberExpression",
                        "computed": false,
                        "object": {
                          "type": "Identifier",
                          "name": "path"
                        },
                        "property": {
                          "type": "Identifier",
                          "name": "join"
                        }
                      },
                      "arguments": [
                        {
                          "type": "MemberExpression",
                          "computed": false,
                          "object": {
                            "type": "Identifier",
                            "name": "common"
                          },
                          "property": {
                            "type": "Identifier",
                            "name": "fixturesDir"
                          }
                        },
                        {
                          "type": "Literal",
                          "value": "test_cert.pem"
                        }
                      ]
                    }
                  ]
                },
                "kind": "init"
              }
            ]
          }
        }
      ],
      "kind": "var"
    },
    {
      "type": "VariableDeclaration",
      "declarations": [
        {
          "type": "VariableDeclarator",
          "id": {
            "type": "Identifier",
            "name": "server"
          },
          "init": {
            "type": "CallExpression",
            "callee": {
              "type": "MemberExpression",
              "computed": false,
              "object": {
                "type": "CallExpression",
                "callee": {
                  "type": "MemberExpression",
                  "computed": false,
                  "object": {
                    "type": "Identifier",
                    "name": "tls"
                  },
                  "property": {
                    "type": "Identifier",
                    "name": "createServer"
                  }
                },
                "arguments": [
                  {
                    "type": "Identifier",
                    "name": "options"
                  },
                  {
                    "type": "FunctionExpression",
                    "id": null,
                    "params": [
                      {
                        "type": "Identifier",
                        "name": "socket"
                      }
                    ],
                    "defaults": [],
                    "body": {
                      "type": "BlockStatement",
                      "body": [
                        {
                          "type": "ExpressionStatement",
                          "expression": {
                            "type": "UpdateExpression",
                            "operator": "++",
                            "argument": {
                              "type": "Identifier",
                              "name": "serverConnected"
                            },
                            "prefix": false
                          }
                        },
                        {
                          "type": "ExpressionStatement",
                          "expression": {
                            "type": "CallExpression",
                            "callee": {
                              "type": "MemberExpression",
                              "computed": false,
                              "object": {
                                "type": "Identifier",
                                "name": "socket"
                              },
                              "property": {
                                "type": "Identifier",
                                "name": "end"
                              }
                            },
                            "arguments": [
                              {
                                "type": "Literal",
                                "value": "Hello"
                              }
                            ]
                          }
                        }
                      ]
                    },
                    "rest": null,
                    "generator": false,
                    "expression": false
                  }
                ]
              },
              "property": {
                "type": "Identifier",
                "name": "listen"
              }
            },
            "arguments": [
              {
                "type": "MemberExpression",
                "computed": false,
                "object": {
                  "type": "Identifier",
                  "name": "common"
                },
                "property": {
                  "type": "Identifier",
                  "name": "PORT"
                }
              },
              {
                "type": "FunctionExpression",
                "id": null,
                "params": [],
                "defaults": [],
                "body": {
                  "type": "BlockStatement",
                  "body": [
                    {
                      "type": "VariableDeclaration",
                      "declarations": [
                        {
                          "type": "VariableDeclarator",
                          "id": {
                            "type": "Identifier",
                            "name": "waiting"
                          },
                          "init": {
                            "type": "Literal",
                            "value": 2
                          }
                        }
                      ],
                      "kind": "var"
                    },
                    {
                      "type": "FunctionDeclaration",
                      "id": {
                        "type": "Identifier",
                        "name": "establish"
                      },
                      "params": [
                        {
                          "type": "Identifier",
                          "name": "socket"
                        }
                      ],
                      "defaults": [],
                      "body": {
                        "type": "BlockStatement",
                        "body": [
                          {
                            "type": "VariableDeclaration",
                            "declarations": [
                              {
                                "type": "VariableDeclarator",
                                "id": {
                                  "type": "Identifier",
                                  "name": "client"
                                },
                                "init": {
                                  "type": "CallExpression",
                                  "callee": {
                                    "type": "MemberExpression",
                                    "computed": false,
                                    "object": {
                                      "type": "Identifier",
                                      "name": "tls"
                                    },
                                    "property": {
                                      "type": "Identifier",
                                      "name": "connect"
                                    }
                                  },
                                  "arguments": [
                                    {
                                      "type": "ObjectExpression",
                                      "properties": [
                                        {
                                          "type": "Property",
                                          "key": {
                                            "type": "Identifier",
                                            "name": "rejectUnauthorized"
                                          },
                                          "value": {
                                            "type": "Literal",
                                            "value": false
                                          },
                                          "kind": "init"
                                        },
                                        {
                                          "type": "Property",
                                          "key": {
                                            "type": "Identifier",
                                            "name": "socket"
                                          },
                                          "value": {
                                            "type": "Identifier",
                                            "name": "socket"
                                          },
                                          "kind": "init"
                                        }
                                      ]
                                    },
                                    {
                                      "type": "FunctionExpression",
                                      "id": null,
                                      "params": [],
                                      "defaults": [],
                                      "body": {
                                        "type": "BlockStatement",
                                        "body": [
                                          {
                                            "type": "ExpressionStatement",
                                            "expression": {
                                              "type": "UpdateExpression",
                                              "operator": "++",
                                              "argument": {
                                                "type": "Identifier",
                                                "name": "clientConnected"
                                              },
                                              "prefix": false
                                            }
                                          },
                                          {
                                            "type": "VariableDeclaration",
                                            "declarations": [
                                              {
                                                "type": "VariableDeclarator",
                                                "id": {
                                                  "type": "Identifier",
                                                  "name": "data"
                                                },
                                                "init": {
                                                  "type": "Literal",
                                                  "value": ""
                                                }
                                              }
                                            ],
                                            "kind": "var"
                                          },
                                          {
                                            "type": "ExpressionStatement",
                                            "expression": {
                                              "type": "CallExpression",
                                              "callee": {
                                                "type": "MemberExpression",
                                                "computed": false,
                                                "object": {
                                                  "type": "Identifier",
                                                  "name": "client"
                                                },
                                                "property": {
                                                  "type": "Identifier",
                                                  "name": "on"
                                                }
                                              },
                                              "arguments": [
                                                {
                                                  "type": "Literal",
                                                  "value": "data"
                                                },
                                                {
                                                  "type": "FunctionExpression",
                                                  "id": null,
                                                  "params": [
                                                    {
                                                      "type": "Identifier",
                                                      "name": "chunk"
                                                    }
                                                  ],
                                                  "defaults": [],
                                                  "body": {
                                                    "type": "BlockStatement",
                                                    "body": [
                                                      {
                                                        "type": "ExpressionStatement",
                                                        "expression": {
                                                          "type": "AssignmentExpression",
                                                          "operator": "+=",
                                                          "left": {
                                                            "type": "Identifier",
                                                            "name": "data"
                                                          },
                                                          "right": {
                                                            "type": "CallExpression",
                                                            "callee": {
                                                              "type": "MemberExpression",
                                                              "computed": false,
                                                              "object": {
                                                                "type": "Identifier",
                                                                "name": "chunk"
                                                              },
                                                              "property": {
                                                                "type": "Identifier",
                                                                "name": "toString"
                                                              }
                                                            },
                                                            "arguments": []
                                                          }
                                                        }
                                                      }
                                                    ]
                                                  },
                                                  "rest": null,
                                                  "generator": false,
                                                  "expression": false
                                                }
                                              ]
                                            }
                                          },
                                          {
                                            "type": "ExpressionStatement",
                                            "expression": {
                                              "type": "CallExpression",
                                              "callee": {
                                                "type": "MemberExpression",
                                                "computed": false,
                                                "object": {
                                                  "type": "Identifier",
                                                  "name": "client"
                                                },
                                                "property": {
                                                  "type": "Identifier",
                                                  "name": "on"
                                                }
                                              },
                                              "arguments": [
                                                {
                                                  "type": "Literal",
                                                  "value": "end"
                                                },
                                                {
                                                  "type": "FunctionExpression",
                                                  "id": null,
                                                  "params": [],
                                                  "defaults": [],
                                                  "body": {
                                                    "type": "BlockStatement",
                                                    "body": [
                                                      {
                                                        "type": "ExpressionStatement",
                                                        "expression": {
                                                          "type": "CallExpression",
                                                          "callee": {
                                                            "type": "MemberExpression",
                                                            "computed": false,
                                                            "object": {
                                                              "type": "Identifier",
                                                              "name": "assert"
                                                            },
                                                            "property": {
                                                              "type": "Identifier",
                                                              "name": "equal"
                                                            }
                                                          },
                                                          "arguments": [
                                                            {
                                                              "type": "Identifier",
                                                              "name": "data"
                                                            },
                                                            {
                                                              "type": "Literal",
                                                              "value": "Hello"
                                                            }
                                                          ]
                                                        }
                                                      },
                                                      {
                                                        "type": "IfStatement",
                                                        "test": {
                                                          "type": "BinaryExpression",
                                                          "operator": "===",
                                                          "left": {
                                                            "type": "UpdateExpression",
                                                            "operator": "--",
                                                            "argument": {
                                                              "type": "Identifier",
                                                              "name": "waiting"
                                                            },
                                                            "prefix": true
                                                          },
                                                          "right": {
                                                            "type": "Literal",
                                                            "value": 0
                                                          }
                                                        },
                                                        "consequent": {
                                                          "type": "ExpressionStatement",
                                                          "expression": {
                                                            "type": "CallExpression",
                                                            "callee": {
                                                              "type": "MemberExpression",
                                                              "computed": false,
                                                              "object": {
                                                                "type": "Identifier",
                                                                "name": "server"
                                                              },
                                                              "property": {
                                                                "type": "Identifier",
                                                                "name": "close"
                                                              }
                                                            },
                                                            "arguments": []
                                                          }
                                                        },
                                                        "alternate": null
                                                      }
                                                    ]
                                                  },
                                                  "rest": null,
                                                  "generator": false,
                                                  "expression": false
                                                }
                                              ]
                                            }
                                          }
                                        ]
                                      },
                                      "rest": null,
                                      "generator": false,
                                      "expression": false
                                    }
                                  ]
                                }
                              }
                            ],
                            "kind": "var"
                          },
                          {
                            "type": "ExpressionStatement",
                            "expression": {
                              "type": "CallExpression",
                              "callee": {
                                "type": "Identifier",
                                "name": "assert"
                              },
                              "arguments": [
                                {
                                  "type": "MemberExpression",
                                  "computed": false,
                                  "object": {
                                    "type": "Identifier",
                                    "name": "client"
                                  },
                                  "property": {
                                    "type": "Identifier",
                                    "name": "readable"
                                  }
                                }
                              ]
                            }
                          },
                          {
                            "type": "ExpressionStatement",
                            "expression": {
                              "type": "CallExpression",
                              "callee": {
                                "type": "Identifier",
                                "name": "assert"
                              },
                              "arguments": [
                                {
                                  "type": "MemberExpression",
                                  "computed": false,
                                  "object": {
                                    "type": "Identifier",
                                    "name": "client"
                                  },
                                  "property": {
                                    "type": "Identifier",
                                    "name": "writable"
                                  }
                                }
                              ]
                            }
                          }
                        ]
                      },
                      "rest": null,
                      "generator": false,
                      "expression": false
                    },
                    {
                      "type": "VariableDeclaration",
                      "declarations": [
                        {
                          "type": "VariableDeclarator",
                          "id": {
                            "type": "Identifier",
                            "name": "connected"
                          },
                          "init": {
                            "type": "CallExpression",
                            "callee": {
                              "type": "MemberExpression",
                              "computed": false,
                              "object": {
                                "type": "Identifier",
                                "name": "net"
                              },
                              "property": {
                                "type": "Identifier",
                                "name": "connect"
                              }
                            },
                            "arguments": [
                              {
                                "type": "MemberExpression",
                                "computed": false,
                                "object": {
                                  "type": "Identifier",
                                  "name": "common"
                                },
                                "property": {
                                  "type": "Identifier",
                                  "name": "PORT"
                                }
                              },
                              {
                                "type": "FunctionExpression",
                                "id": null,
                                "params": [],
                                "defaults": [],
                                "body": {
                                  "type": "BlockStatement",
                                  "body": [
                                    {
                                      "type": "ExpressionStatement",
                                      "expression": {
                                        "type": "CallExpression",
                                        "callee": {
                                          "type": "Identifier",
                                          "name": "establish"
                                        },
                                        "arguments": [
                                          {
                                            "type": "Identifier",
                                            "name": "connected"
                                          }
                                        ]
                                      }
                                    }
                                  ]
                                },
                                "rest": null,
                                "generator": false,
                                "expression": false
                              }
                            ]
                          }
                        }
                      ],
                      "kind": "var"
                    },
                    {
                      "type": "VariableDeclaration",
                      "declarations": [
                        {
                          "type": "VariableDeclarator",
                          "id": {
                            "type": "Identifier",
                            "name": "connecting"
                          },
                          "init": {
                            "type": "CallExpression",
                            "callee": {
                              "type": "MemberExpression",
                              "computed": false,
                              "object": {
                                "type": "Identifier",
                                "name": "net"
                              },
                              "property": {
                                "type": "Identifier",
                                "name": "connect"
                              }
                            },
                            "arguments": [
                              {
                                "type": "MemberExpression",
                                "computed": false,
                                "object": {
                                  "type": "Identifier",
                                  "name": "common"
                                },
                                "property": {
                                  "type": "Identifier",
                                  "name": "PORT"
                                }
                              }
                            ]
                          }
                        }
                      ],
                      "kind": "var"
                    },
                    {
                      "type": "ExpressionStatement",
                      "expression": {
                        "type": "CallExpression",
                        "callee": {
                          "type": "Identifier",
                          "name": "establish"
                        },
                        "arguments": [
                          {
                            "type": "Identifier",
                            "name": "connecting"
                          }
                        ]
                      }
                    }
                  ]
                },
                "rest": null,
                "generator": false,
                "expression": false
              }
            ]
          }
        }
      ],
      "kind": "var"
    },
    {
      "type": "ExpressionStatement",
      "expression": {
        "type": "CallExpression",
        "callee": {
          "type": "MemberExpression",
          "computed": false,
          "object": {
            "type": "Identifier",
            "name": "process"
          },
          "property": {
            "type": "Identifier",
            "name": "on"
          }
        },
        "arguments": [
          {
            "type": "Literal",
            "value": "exit"
          },
          {
            "type": "FunctionExpression",
            "id": null,
            "params": [],
            "defaults": [],
            "body": {
              "type": "BlockStatement",
              "body": [
                {
                  "type": "ExpressionStatement",
                  "expression": {
                    "type": "CallExpression",
                    "callee": {
                      "type": "MemberExpression",
                      "computed": false,
                      "object": {
                        "type": "Identifier",
                        "name": "assert"
                      },
                      "property": {
                        "type": "Identifier",
                        "name": "equal"
                      }
                    },
                    "arguments": [
                      {
                        "type": "Identifier",
                        "name": "serverConnected"
                      },
                      {
                        "type": "Literal",
                        "value": 2
                      }
                    ]
                  }
                },
                {
                  "type": "ExpressionStatement",
                  "expression": {
                    "type": "CallExpression",
                    "callee": {
                      "type": "MemberExpression",
                      "computed": false,
                      "object": {
                        "type": "Identifier",
                        "name": "assert"
                      },
                      "property": {
                        "type": "Identifier",
                        "name": "equal"
                      }
                    },
                    "arguments": [
                      {
                        "type": "Identifier",
                        "name": "clientConnected"
                      },
                      {
                        "type": "Literal",
                        "value": 2
                      }
                    ]
                  }
                }
              ]
            },
            "rest": null,
            "generator": false,
            "expression": false
          }
        ]
      }
    }
  ]
}