{
  "type": "Program",
  "body": [
    {
      "type": "ExpressionStatement",
      "expression": {
        "type": "AssignmentExpression",
        "operator": "=",
        "left": {
          "type": "MemberExpression",
          "computed": false,
          "object": {
            "type": "Identifier",
            "name": "Date"
          },
          "property": {
            "type": "Identifier",
            "name": "CultureStrings"
          }
        },
        "right": {
          "type": "LogicalExpression",
          "operator": "||",
          "left": {
            "type": "MemberExpression",
            "computed": false,
            "object": {
              "type": "Identifier",
              "name": "Date"
            },
            "property": {
              "type": "Identifier",
              "name": "CultureStrings"
            }
          },
          "right": {
            "type": "ObjectExpression",
            "properties": []
          }
        }
      }
    },
    {
      "type": "ExpressionStatement",
      "expression": {
        "type": "AssignmentExpression",
        "operator": "=",
        "left": {
          "type": "MemberExpression",
          "computed": true,
          "object": {
            "type": "MemberExpression",
            "computed": false,
            "object": {
              "type": "Identifier",
              "name": "Date"
            },
            "property": {
              "type": "Identifier",
              "name": "CultureStrings"
            }
          },
          "property": {
            "type": "Literal",
            "value": "es-EC"
          }
        },
        "right": {
          "type": "ObjectExpression",
          "properties": [
            {
              "type": "Property",
              "key": {
                "type": "Literal",
                "value": "name"
              },
              "value": {
                "type": "Literal",
                "value": "es-EC"
              },
              "kind": "init"
            },
            {
              "type": "Property",
              "key": {
                "type": "Literal",
                "value": "englishName"
              },
              "value": {
                "type": "Literal",
                "value": "Spanish (Ecuador)"
              },
              "kind": "init"
            },
            {
              "type": "Property",
              "key": {
                "type": "Literal",
                "value": "nativeName"
              },
              "value": {
                "type": "Literal",
                "value": "Español (Ecuador)"
              },
              "kind": "init"
            },
            {
              "type": "Property",
              "key": {
                "type": "Literal",
                "value": "Sunday"
              },
              "value": {
                "type": "Literal",
                "value": "domingo"
              },
              "kind": "init"
            },
            {
              "type": "Property",
              "key": {
                "type": "Literal",
                "value": "Monday"
              },
              "value": {
                "type": "Literal",
                "value": "lunes"
              },
              "kind": "init"
            },
            {
              "type": "Property",
              "key": {
                "type": "Literal",
                "value": "Tuesday"
              },
              "value": {
                "type": "Literal",
                "value": "martes"
              },
              "kind": "init"
            },
            {
              "type": "Property",
              "key": {
                "type": "Literal",
                "value": "Wednesday"
              },
              "value": {
                "type": "Literal",
                "value": "miércoles"
              },
              "kind": "init"
            },
            {
              "type": "Property",
              "key": {
                "type": "Literal",
                "value": "Thursday"
              },
              "value": {
                "type": "Literal",
                "value": "jueves"
              },
              "kind": "init"
            },
            {
              "type": "Property",
              "key": {
                "type": "Literal",
                "value": "Friday"
              },
              "value": {
                "type": "Literal",
                "value": "viernes"
              },
              "kind": "init"
            },
            {
              "type": "Property",
              "key": {
                "type": "Literal",
                "value": "Saturday"
              },
              "value": {
                "type": "Literal",
                "value": "sábado"
              },
              "kind": "init"
            },
            {
              "type": "Property",
              "key": {
                "type": "Literal",
                "value": "Sun"
              },
              "value": {
                "type": "Literal",
                "value": "dom"
              },
              "kind": "init"
            },
            {
              "type": "Property",
              "key": {
                "type": "Literal",
                "value": "Mon"
              },
              "value": {
                "type": "Literal",
                "value": "lun"
              },
              "kind": "init"
            },
            {
              "type": "Property",
              "key": {
                "type": "Literal",
                "value": "Tue"
              },
              "value": {
                "type": "Literal",
                "value": "mar"
              },
              "kind": "init"
            },
            {
              "type": "Property",
              "key": {
                "type": "Literal",
                "value": "Wed"
              },
              "value": {
                "type": "Literal",
                "value": "mié"
              },
              "kind": "init"
            },
            {
              "type": "Property",
              "key": {
                "type": "Literal",
                "value": "Thu"
              },
              "value": {
                "type": "Literal",
                "value": "jue"
              },
              "kind": "init"
            },
            {
              "type": "Property",
              "key": {
                "type": "Literal",
                "value": "Fri"
              },
              "value": {
                "type": "Literal",
                "value": "vie"
              },
              "kind": "init"
            },
            {
              "type": "Property",
              "key": {
                "type": "Literal",
                "value": "Sat"
              },
              "value": {
                "type": "Literal",
                "value": "sáb"
              },
              "kind": "init"
            },
            {
              "type": "Property",
              "key": {
                "type": "Literal",
                "value": "Su"
              },
              "value": {
                "type": "Literal",
                "value": "do"
              },
              "kind": "init"
            },
            {
              "type": "Property",
              "key": {
                "type": "Literal",
                "value": "Mo"
              },
              "value": {
                "type": "Literal",
                "value": "lu"
              },
              "kind": "init"
            },
            {
              "type": "Property",
              "key": {
                "type": "Literal",
                "value": "Tu"
              },
              "value": {
                "type": "Literal",
                "value": "ma"
              },
              "kind": "init"
            },
            {
              "type": "Property",
              "key": {
                "type": "Literal",
                "value": "We"
              },
              "value": {
                "type": "Literal",
                "value": "mi"
              },
              "kind": "init"
            },
            {
              "type": "Property",
              "key": {
                "type": "Literal",
                "value": "Th"
              },
              "value": {
                "type": "Literal",
                "value": "ju"
              },
              "kind": "init"
            },
            {
              "type": "Property",
              "key": {
                "type": "Literal",
                "value": "Fr"
              },
              "value": {
                "type": "Literal",
                "value": "vi"
              },
              "kind": "init"
            },
            {
              "type": "Property",
              "key": {
                "type": "Literal",
                "value": "Sa"
              },
              "value": {
                "type": "Literal",
                "value": "sá"
              },
              "kind": "init"
            },
            {
              "type": "Property",
              "key": {
                "type": "Literal",
                "value": "S_Sun_Initial"
              },
              "value": {
                "type": "Literal",
                "value": "d"
              },
              "kind": "init"
            },
            {
              "type": "Property",
              "key": {
                "type": "Literal",
                "value": "M_Mon_Initial"
              },
              "value": {
                "type": "Literal",
                "value": "l"
              },
              "kind": "init"
            },
            {
              "type": "Property",
              "key": {
                "type": "Literal",
                "value": "T_Tue_Initial"
              },
              "value": {
                "type": "Literal",
                "value": "m"
              },
              "kind": "init"
            },
            {
              "type": "Property",
              "key": {
                "type": "Literal",
                "value": "W_Wed_Initial"
              },
              "value": {
                "type": "Literal",
                "value": "m"
              },
              "kind": "init"
            },
            {
              "type": "Property",
              "key": {
                "type": "Literal",
                "value": "T_Thu_Initial"
              },
              "value": {
                "type": "Literal",
                "value": "j"
              },
              "kind": "init"
            },
            {
              "type": "Property",
              "key": {
                "type": "Literal",
                "value": "F_Fri_Initial"
              },
              "value": {
                "type": "Literal",
                "value": "v"
              },
              "kind": "init"
            },
            {
              "type": "Property",
              "key": {
                "type": "Literal",
                "value": "S_Sat_Initial"
              },
              "value": {
                "type": "Literal",
                "value": "s"
              },
              "kind": "init"
            },
            {
              "type": "Property",
              "key": {
                "type": "Literal",
                "value": "January"
              },
              "value": {
                "type": "Literal",
                "value": "enero"
              },
              "kind": "init"
            },
            {
              "type": "Property",
              "key": {
                "type": "Literal",
                "value": "February"
              },
              "value": {
                "type": "Literal",
                "value": "febrero"
              },
              "kind": "init"
            },
            {
              "type": "Property",
              "key": {
                "type": "Literal",
                "value": "March"
              },
              "value": {
                "type": "Literal",
                "value": "marzo"
              },
              "kind": "init"
            },
            {
              "type": "Property",
              "key": {
                "type": "Literal",
                "value": "April"
              },
              "value": {
                "type": "Literal",
                "value": "abril"
              },
              "kind": "init"
            },
            {
              "type": "Property",
              "key": {
                "type": "Literal",
                "value": "May"
              },
              "value": {
                "type": "Literal",
                "value": "mayo"
              },
              "kind": "init"
            },
            {
              "type": "Property",
              "key": {
                "type": "Literal",
                "value": "June"
              },
              "value": {
                "type": "Literal",
                "value": "junio"
              },
              "kind": "init"
            },
            {
              "type": "Property",
              "key": {
                "type": "Literal",
                "value": "July"
              },
              "value": {
                "type": "Literal",
                "value": "julio"
              },
              "kind": "init"
            },
            {
              "type": "Property",
              "key": {
                "type": "Literal",
                "value": "August"
              },
              "value": {
                "type": "Literal",
                "value": "agosto"
              },
              "kind": "init"
            },
            {
              "type": "Property",
              "key": {
                "type": "Literal",
                "value": "September"
              },
              "value": {
                "type": "Literal",
                "value": "septiembre"
              },
              "kind": "init"
            },
            {
              "type": "Property",
              "key": {
                "type": "Literal",
                "value": "October"
              },
              "value": {
                "type": "Literal",
                "value": "octubre"
              },
              "kind": "init"
            },
            {
              "type": "Property",
              "key": {
                "type": "Literal",
                "value": "November"
              },
              "value": {
                "type": "Literal",
                "value": "noviembre"
              },
              "kind": "init"
            },
            {
              "type": "Property",
              "key": {
                "type": "Literal",
                "value": "December"
              },
              "value": {
                "type": "Literal",
                "value": "diciembre"
              },
              "kind": "init"
            },
            {
              "type": "Property",
              "key": {
                "type": "Literal",
                "value": "Jan_Abbr"
              },
              "value": {
                "type": "Literal",
                "value": "ene"
              },
              "kind": "init"
            },
            {
              "type": "Property",
              "key": {
                "type": "Literal",
                "value": "Feb_Abbr"
              },
              "value": {
                "type": "Literal",
                "value": "feb"
              },
              "kind": "init"
            },
            {
              "type": "Property",
              "key": {
                "type": "Literal",
                "value": "Mar_Abbr"
              },
              "value": {
                "type": "Literal",
                "value": "mar"
              },
              "kind": "init"
            },
            {
              "type": "Property",
              "key": {
                "type": "Literal",
                "value": "Apr_Abbr"
              },
              "value": {
                "type": "Literal",
                "value": "abr"
              },
              "kind": "init"
            },
            {
              "type": "Property",
              "key": {
                "type": "Literal",
                "value": "May_Abbr"
              },
              "value": {
                "type": "Literal",
                "value": "may"
              },
              "kind": "init"
            },
            {
              "type": "Property",
              "key": {
                "type": "Literal",
                "value": "Jun_Abbr"
              },
              "value": {
                "type": "Literal",
                "value": "jun"
              },
              "kind": "init"
            },
            {
              "type": "Property",
              "key": {
                "type": "Literal",
                "value": "Jul_Abbr"
              },
              "value": {
                "type": "Literal",
                "value": "jul"
              },
              "kind": "init"
            },
            {
              "type": "Property",
              "key": {
                "type": "Literal",
                "value": "Aug_Abbr"
              },
              "value": {
                "type": "Literal",
                "value": "ago"
              },
              "kind": "init"
            },
            {
              "type": "Property",
              "key": {
                "type": "Literal",
                "value": "Sep_Abbr"
              },
              "value": {
                "type": "Literal",
                "value": "sep"
              },
              "kind": "init"
            },
            {
              "type": "Property",
              "key": {
                "type": "Literal",
                "value": "Oct_Abbr"
              },
              "value": {
                "type": "Literal",
                "value": "oct"
              },
              "kind": "init"
            },
            {
              "type": "Property",
              "key": {
                "type": "Literal",
                "value": "Nov_Abbr"
              },
              "value": {
                "type": "Literal",
                "value": "nov"
              },
              "kind": "init"
            },
            {
              "type": "Property",
              "key": {
                "type": "Literal",
                "value": "Dec_Abbr"
              },
              "value": {
                "type": "Literal",
                "value": "dic"
              },
              "kind": "init"
            },
            {
              "type": "Property",
              "key": {
                "type": "Literal",
                "value": "AM"
              },
              "value": {
                "type": "Literal",
                "value": ""
              },
              "kind": "init"
            },
            {
              "type": "Property",
              "key": {
                "type": "Literal",
                "value": "PM"
              },
              "value": {
                "type": "Literal",
                "value": ""
              },
              "kind": "init"
            },
            {
              "type": "Property",
              "key": {
                "type": "Literal",
                "value": "firstDayOfWeek"
              },
              "value": {
                "type": "Literal",
                "value": 0
              },
              "kind": "init"
            },
            {
              "type": "Property",
              "key": {
                "type": "Literal",
                "value": "twoDigitYearMax"
              },
              "value": {
                "type": "Literal",
                "value": 2029
              },
              "kind": "init"
            },
            {
              "type": "Property",
              "key": {
                "type": "Literal",
                "value": "mdy"
              },
              "value": {
                "type": "Literal",
                "value": "dmy"
              },
              "kind": "init"
            },
            {
              "type": "Property",
              "key": {
                "type": "Literal",
                "value": "M/d/yyyy"
              },
              "value": {
                "type": "Literal",
                "value": "dd/MM/yyyy"
              },
              "kind": "init"
            },
            {
              "type": "Property",
              "key": {
                "type": "Literal",
                "value": "dddd, MMMM dd, yyyy"
              },
              "value": {
                "type": "Literal",
                "value": "dddd, dd' [de] 'MMMM' [de] 'yyyy"
              },
              "kind": "init"
            },
            {
              "type": "Property",
              "key": {
                "type": "Literal",
                "value": "h:mm tt"
              },
              "value": {
                "type": "Literal",
                "value": "H:mm"
              },
              "kind": "init"
            },
            {
              "type": "Property",
              "key": {
                "type": "Literal",
                "value": "h:mm:ss tt"
              },
              "value": {
                "type": "Literal",
                "value": "H:mm:ss"
              },
              "kind": "init"
            },
            {
              "type": "Property",
              "key": {
                "type": "Literal",
                "value": "dddd, MMMM dd, yyyy h:mm:ss tt"
              },
              "value": {
                "type": "Literal",
                "value": "dddd, dd' [de] 'MMMM' [de] 'yyyy H:mm:ss"
              },
              "kind": "init"
            },
            {
              "type": "Property",
              "key": {
                "type": "Literal",
                "value": "yyyy-MM-ddTHH:mm:ss"
              },
              "value": {
                "type": "Literal",
                "value": "yyyy-MM-ddTHH:mm:ss"
              },
              "kind": "init"
            },
            {
              "type": "Property",
              "key": {
                "type": "Literal",
                "value": "yyyy-MM-dd HH:mm:ssZ"
              },
              "value": {
                "type": "Literal",
                "value": "yyyy-MM-dd HH:mm:ssZ"
              },
              "kind": "init"
            },
            {
              "type": "Property",
              "key": {
                "type": "Literal",
                "value": "ddd, dd MMM yyyy HH:mm:ss"
              },
              "value": {
                "type": "Literal",
                "value": "ddd, dd MMM yyyy HH:mm:ss"
              },
              "kind": "init"
            },
            {
              "type": "Property",
              "key": {
                "type": "Literal",
                "value": "MMMM dd"
              },
              "value": {
                "type": "Literal",
                "value": "dd MMMM"
              },
              "kind": "init"
            },
            {
              "type": "Property",
              "key": {
                "type": "Literal",
                "value": "MMMM, yyyy"
              },
              "value": {
                "type": "Literal",
                "value": "MMMM' [de] 'yyyy"
              },
              "kind": "init"
            },
            {
              "type": "Property",
              "key": {
                "type": "Literal",
                "value": "/jan(uary)?/"
              },
              "value": {
                "type": "Literal",
                "value": "ene(ro)?"
              },
              "kind": "init"
            },
            {
              "type": "Property",
              "key": {
                "type": "Literal",
                "value": "/feb(ruary)?/"
              },
              "value": {
                "type": "Literal",
                "value": "feb(rero)?"
              },
              "kind": "init"
            },
            {
              "type": "Property",
              "key": {
                "type": "Literal",
                "value": "/mar(ch)?/"
              },
              "value": {
                "type": "Literal",
                "value": "mar(zo)?"
              },
              "kind": "init"
            },
            {
              "type": "Property",
              "key": {
                "type": "Literal",
                "value": "/apr(il)?/"
              },
              "value": {
                "type": "Literal",
                "value": "abr(il)?"
              },
              "kind": "init"
            },
            {
              "type": "Property",
              "key": {
                "type": "Literal",
                "value": "/may/"
              },
              "value": {
                "type": "Literal",
                "value": "may(o)?"
              },
              "kind": "init"
            },
            {
              "type": "Property",
              "key": {
                "type": "Literal",
                "value": "/jun(e)?/"
              },
              "value": {
                "type": "Literal",
                "value": "jun(io)?"
              },
              "kind": "init"
            },
            {
              "type": "Property",
              "key": {
                "type": "Literal",
                "value": "/jul(y)?/"
              },
              "value": {
                "type": "Literal",
                "value": "jul(io)?"
              },
              "kind": "init"
            },
            {
              "type": "Property",
              "key": {
                "type": "Literal",
                "value": "/aug(ust)?/"
              },
              "value": {
                "type": "Literal",
                "value": "ago(sto)?"
              },
              "kind": "init"
            },
            {
              "type": "Property",
              "key": {
                "type": "Literal",
                "value": "/sep(t(ember)?)?/"
              },
              "value": {
                "type": "Literal",
                "value": "sep(tiembre)?"
              },
              "kind": "init"
            },
            {
              "type": "Property",
              "key": {
                "type": "Literal",
                "value": "/oct(ober)?/"
              },
              "value": {
                "type": "Literal",
                "value": "oct(ubre)?"
              },
              "kind": "init"
            },
            {
              "type": "Property",
              "key": {
                "type": "Literal",
                "value": "/nov(ember)?/"
              },
              "value": {
                "type": "Literal",
                "value": "nov(iembre)?"
              },
              "kind": "init"
            },
            {
              "type": "Property",
              "key": {
                "type": "Literal",
                "value": "/dec(ember)?/"
              },
              "value": {
                "type": "Literal",
                "value": "dic(iembre)?"
              },
              "kind": "init"
            },
            {
              "type": "Property",
              "key": {
                "type": "Literal",
                "value": "/^su(n(day)?)?/"
              },
              "value": {
                "type": "Literal",
                "value": "^do(m(ingo)?)?"
              },
              "kind": "init"
            },
            {
              "type": "Property",
              "key": {
                "type": "Literal",
                "value": "/^mo(n(day)?)?/"
              },
              "value": {
                "type": "Literal",
                "value": "^lu(n(es)?)?"
              },
              "kind": "init"
            },
            {
              "type": "Property",
              "key": {
                "type": "Literal",
                "value": "/^tu(e(s(day)?)?)?/"
              },
              "value": {
                "type": "Literal",
                "value": "^ma(r(tes)?)?"
              },
              "kind": "init"
            },
            {
              "type": "Property",
              "key": {
                "type": "Literal",
                "value": "/^we(d(nesday)?)?/"
              },
              "value": {
                "type": "Literal",
                "value": "^mi(é(rcoles)?)?"
              },
              "kind": "init"
            },
            {
              "type": "Property",
              "key": {
                "type": "Literal",
                "value": "/^th(u(r(s(day)?)?)?)?/"
              },
              "value": {
                "type": "Literal",
                "value": "^ju(e(ves)?)?"
              },
              "kind": "init"
            },
            {
              "type": "Property",
              "key": {
                "type": "Literal",
                "value": "/^fr(i(day)?)?/"
              },
              "value": {
                "type": "Literal",
                "value": "^vi(e(rnes)?)?"
              },
              "kind": "init"
            },
            {
              "type": "Property",
              "key": {
                "type": "Literal",
                "value": "/^sa(t(urday)?)?/"
              },
              "value": {
                "type": "Literal",
                "value": "^sá(b(ado)?)?"
              },
              "kind": "init"
            },
            {
              "type": "Property",
              "key": {
                "type": "Literal",
                "value": "/^next/"
              },
              "value": {
                "type": "Literal",
                "value": "^next"
              },
              "kind": "init"
            },
            {
              "type": "Property",
              "key": {
                "type": "Literal",
                "value": "/^last|past|prev(ious)?/"
              },
              "value": {
                "type": "Literal",
                "value": "^last|past|prev(ious)?"
              },
              "kind": "init"
            },
            {
              "type": "Property",
              "key": {
                "type": "Literal",
                "value": "/^(\\+|aft(er)?|from|hence)/"
              },
              "value": {
                "type": "Literal",
                "value": "^(\\+|aft(er)?|from|hence)"
              },
              "kind": "init"
            },
            {
              "type": "Property",
              "key": {
                "type": "Literal",
                "value": "/^(\\-|bef(ore)?|ago)/"
              },
              "value": {
                "type": "Literal",
                "value": "^(\\-|bef(ore)?|ago)"
              },
              "kind": "init"
            },
            {
              "type": "Property",
              "key": {
                "type": "Literal",
                "value": "/^yes(terday)?/"
              },
              "value": {
                "type": "Literal",
                "value": "^yes(terday)?"
              },
              "kind": "init"
            },
            {
              "type": "Property",
              "key": {
                "type": "Literal",
                "value": "/^t(od(ay)?)?/"
              },
              "value": {
                "type": "Literal",
                "value": "^t(od(ay)?)?"
              },
              "kind": "init"
            },
            {
              "type": "Property",
              "key": {
                "type": "Literal",
                "value": "/^tom(orrow)?/"
              },
              "value": {
                "type": "Literal",
                "value": "^tom(orrow)?"
              },
              "kind": "init"
            },
            {
              "type": "Property",
              "key": {
                "type": "Literal",
                "value": "/^n(ow)?/"
              },
              "value": {
                "type": "Literal",
                "value": "^n(ow)?"
              },
              "kind": "init"
            },
            {
              "type": "Property",
              "key": {
                "type": "Literal",
                "value": "/^ms|milli(second)?s?/"
              },
              "value": {
                "type": "Literal",
                "value": "^ms|milli(second)?s?"
              },
              "kind": "init"
            },
            {
              "type": "Property",
              "key": {
                "type": "Literal",
                "value": "/^sec(ond)?s?/"
              },
              "value": {
                "type": "Literal",
                "value": "^sec(ond)?s?"
              },
              "kind": "init"
            },
            {
              "type": "Property",
              "key": {
                "type": "Literal",
                "value": "/^mn|min(ute)?s?/"
              },
              "value": {
                "type": "Literal",
                "value": "^mn|min(ute)?s?"
              },
              "kind": "init"
            },
            {
              "type": "Property",
              "key": {
                "type": "Literal",
                "value": "/^h(our)?s?/"
              },
              "value": {
                "type": "Literal",
                "value": "^h(our)?s?"
              },
              "kind": "init"
            },
            {
              "type": "Property",
              "key": {
                "type": "Literal",
                "value": "/^w(eek)?s?/"
              },
              "value": {
                "type": "Literal",
                "value": "^w(eek)?s?"
              },
              "kind": "init"
            },
            {
              "type": "Property",
              "key": {
                "type": "Literal",
                "value": "/^m(onth)?s?/"
              },
              "value": {
                "type": "Literal",
                "value": "^m(onth)?s?"
              },
              "kind": "init"
            },
            {
              "type": "Property",
              "key": {
                "type": "Literal",
                "value": "/^d(ay)?s?/"
              },
              "value": {
                "type": "Literal",
                "value": "^d(ay)?s?"
              },
              "kind": "init"
            },
            {
              "type": "Property",
              "key": {
                "type": "Literal",
                "value": "/^y(ear)?s?/"
              },
              "value": {
                "type": "Literal",
                "value": "^y(ear)?s?"
              },
              "kind": "init"
            },
            {
              "type": "Property",
              "key": {
                "type": "Literal",
                "value": "/^(a|p)/"
              },
              "value": {
                "type": "Literal",
                "value": "^(a|p)"
              },
              "kind": "init"
            },
            {
              "type": "Property",
              "key": {
                "type": "Literal",
                "value": "/^(a\\.?m?\\.?|p\\.?m?\\.?)/"
              },
              "value": {
                "type": "Literal",
                "value": "^(a\\.?m?\\.?|p\\.?m?\\.?)"
              },
              "kind": "init"
            },
            {
              "type": "Property",
              "key": {
                "type": "Literal",
                "value": "/^((e(s|d)t|c(s|d)t|m(s|d)t|p(s|d)t)|((gmt)?\\s*(\\+|\\-)\\s*\\d\\d\\d\\d?)|gmt|utc)/"
              },
              "value": {
                "type": "Literal",
                "value": "^((e(s|d)t|c(s|d)t|m(s|d)t|p(s|d)t)|((gmt)?\\s*(\\+|\\-)\\s*\\d\\d\\d\\d?)|gmt|utc)"
              },
              "kind": "init"
            },
            {
              "type": "Property",
              "key": {
                "type": "Literal",
                "value": "/^\\s*(st|nd|rd|th)/"
              },
              "value": {
                "type": "Literal",
                "value": "^\\s*(st|nd|rd|th)"
              },
              "kind": "init"
            },
            {
              "type": "Property",
              "key": {
                "type": "Literal",
                "value": "/^\\s*(\\:|a(?!u|p)|p)/"
              },
              "value": {
                "type": "Literal",
                "value": "^\\s*(\\:|a(?!u|p)|p)"
              },
              "kind": "init"
            },
            {
              "type": "Property",
              "key": {
                "type": "Literal",
                "value": "LINT"
              },
              "value": {
                "type": "Literal",
                "value": "LINT"
              },
              "kind": "init"
            },
            {
              "type": "Property",
              "key": {
                "type": "Literal",
                "value": "TOT"
              },
              "value": {
                "type": "Literal",
                "value": "TOT"
              },
              "kind": "init"
            },
            {
              "type": "Property",
              "key": {
                "type": "Literal",
                "value": "CHAST"
              },
              "value": {
                "type": "Literal",
                "value": "CHAST"
              },
              "kind": "init"
            },
            {
              "type": "Property",
              "key": {
                "type": "Literal",
                "value": "NZST"
              },
              "value": {
                "type": "Literal",
                "value": "NZST"
              },
              "kind": "init"
            },
            {
              "type": "Property",
              "key": {
                "type": "Literal",
                "value": "NFT"
              },
              "value": {
                "type": "Literal",
                "value": "NFT"
              },
              "kind": "init"
            },
            {
              "type": "Property",
              "key": {
                "type": "Literal",
                "value": "SBT"
              },
              "value": {
                "type": "Literal",
                "value": "SBT"
              },
              "kind": "init"
            },
            {
              "type": "Property",
              "key": {
                "type": "Literal",
                "value": "AEST"
              },
              "value": {
                "type": "Literal",
                "value": "AEST"
              },
              "kind": "init"
            },
            {
              "type": "Property",
              "key": {
                "type": "Literal",
                "value": "ACST"
              },
              "value": {
                "type": "Literal",
                "value": "ACST"
              },
              "kind": "init"
            },
            {
              "type": "Property",
              "key": {
                "type": "Literal",
                "value": "JST"
              },
              "value": {
                "type": "Literal",
                "value": "JST"
              },
              "kind": "init"
            },
            {
              "type": "Property",
              "key": {
                "type": "Literal",
                "value": "CWST"
              },
              "value": {
                "type": "Literal",
                "value": "CWST"
              },
              "kind": "init"
            },
            {
              "type": "Property",
              "key": {
                "type": "Literal",
                "value": "CT"
              },
              "value": {
                "type": "Literal",
                "value": "CT"
              },
              "kind": "init"
            },
            {
              "type": "Property",
              "key": {
                "type": "Literal",
                "value": "ICT"
              },
              "value": {
                "type": "Literal",
                "value": "ICT"
              },
              "kind": "init"
            },
            {
              "type": "Property",
              "key": {
                "type": "Literal",
                "value": "MMT"
              },
              "value": {
                "type": "Literal",
                "value": "MMT"
              },
              "kind": "init"
            },
            {
              "type": "Property",
              "key": {
                "type": "Literal",
                "value": "BIOT"
              },
              "value": {
                "type": "Literal",
                "value": "BST"
              },
              "kind": "init"
            },
            {
              "type": "Property",
              "key": {
                "type": "Literal",
                "value": "NPT"
              },
              "value": {
                "type": "Literal",
                "value": "NPT"
              },
              "kind": "init"
            },
            {
              "type": "Property",
              "key": {
                "type": "Literal",
                "value": "IST"
              },
              "value": {
                "type": "Literal",
                "value": "IST"
              },
              "kind": "init"
            },
            {
              "type": "Property",
              "key": {
                "type": "Literal",
                "value": "PKT"
              },
              "value": {
                "type": "Literal",
                "value": "PKT"
              },
              "kind": "init"
            },
            {
              "type": "Property",
              "key": {
                "type": "Literal",
                "value": "AFT"
              },
              "value": {
                "type": "Literal",
                "value": "AFT"
              },
              "kind": "init"
            },
            {
              "type": "Property",
              "key": {
                "type": "Literal",
                "value": "MSK"
              },
              "value": {
                "type": "Literal",
                "value": "MSK"
              },
              "kind": "init"
            },
            {
              "type": "Property",
              "key": {
                "type": "Literal",
                "value": "IRST"
              },
              "value": {
                "type": "Literal",
                "value": "IRST"
              },
              "kind": "init"
            },
            {
              "type": "Property",
              "key": {
                "type": "Literal",
                "value": "FET"
              },
              "value": {
                "type": "Literal",
                "value": "FET"
              },
              "kind": "init"
            },
            {
              "type": "Property",
              "key": {
                "type": "Literal",
                "value": "EET"
              },
              "value": {
                "type": "Literal",
                "value": "EET"
              },
              "kind": "init"
            },
            {
              "type": "Property",
              "key": {
                "type": "Literal",
                "value": "CET"
              },
              "value": {
                "type": "Literal",
                "value": "CET"
              },
              "kind": "init"
            },
            {
              "type": "Property",
              "key": {
                "type": "Literal",
                "value": "UTC"
              },
              "value": {
                "type": "Literal",
                "value": "UTC"
              },
              "kind": "init"
            },
            {
              "type": "Property",
              "key": {
                "type": "Literal",
                "value": "GMT"
              },
              "value": {
                "type": "Literal",
                "value": "GMT"
              },
              "kind": "init"
            },
            {
              "type": "Property",
              "key": {
                "type": "Literal",
                "value": "CVT"
              },
              "value": {
                "type": "Literal",
                "value": "CVT"
              },
              "kind": "init"
            },
            {
              "type": "Property",
              "key": {
                "type": "Literal",
                "value": "GST"
              },
              "value": {
                "type": "Literal",
                "value": "GST"
              },
              "kind": "init"
            },
            {
              "type": "Property",
              "key": {
                "type": "Literal",
                "value": "BRT"
              },
              "value": {
                "type": "Literal",
                "value": "BRT"
              },
              "kind": "init"
            },
            {
              "type": "Property",
              "key": {
                "type": "Literal",
                "value": "NST"
              },
              "value": {
                "type": "Literal",
                "value": "NST"
              },
              "kind": "init"
            },
            {
              "type": "Property",
              "key": {
                "type": "Literal",
                "value": "AST"
              },
              "value": {
                "type": "Literal",
                "value": "AST"
              },
              "kind": "init"
            },
            {
              "type": "Property",
              "key": {
                "type": "Literal",
                "value": "EST"
              },
              "value": {
                "type": "Literal",
                "value": "EST"
              },
              "kind": "init"
            },
            {
              "type": "Property",
              "key": {
                "type": "Literal",
                "value": "CST"
              },
              "value": {
                "type": "Literal",
                "value": "CST"
              },
              "kind": "init"
            },
            {
              "type": "Property",
              "key": {
                "type": "Literal",
                "value": "MST"
              },
              "value": {
                "type": "Literal",
                "value": "MST"
              },
              "kind": "init"
            },
            {
              "type": "Property",
              "key": {
                "type": "Literal",
                "value": "PST"
              },
              "value": {
                "type": "Literal",
                "value": "PST"
              },
              "kind": "init"
            },
            {
              "type": "Property",
              "key": {
                "type": "Literal",
                "value": "AKST"
              },
              "value": {
                "type": "Literal",
                "value": "AKST"
              },
              "kind": "init"
            },
            {
              "type": "Property",
              "key": {
                "type": "Literal",
                "value": "MIT"
              },
              "value": {
                "type": "Literal",
                "value": "MIT"
              },
              "kind": "init"
            },
            {
              "type": "Property",
              "key": {
                "type": "Literal",
                "value": "HST"
              },
              "value": {
                "type": "Literal",
                "value": "HST"
              },
              "kind": "init"
            },
            {
              "type": "Property",
              "key": {
                "type": "Literal",
                "value": "SST"
              },
              "value": {
                "type": "Literal",
                "value": "SST"
              },
              "kind": "init"
            },
            {
              "type": "Property",
              "key": {
                "type": "Literal",
                "value": "BIT"
              },
              "value": {
                "type": "Literal",
                "value": "BIT"
              },
              "kind": "init"
            },
            {
              "type": "Property",
              "key": {
                "type": "Literal",
                "value": "CHADT"
              },
              "value": {
                "type": "Literal",
                "value": "CHADT"
              },
              "kind": "init"
            },
            {
              "type": "Property",
              "key": {
                "type": "Literal",
                "value": "NZDT"
              },
              "value": {
                "type": "Literal",
                "value": "NZDT"
              },
              "kind": "init"
            },
            {
              "type": "Property",
              "key": {
                "type": "Literal",
                "value": "AEDT"
              },
              "value": {
                "type": "Literal",
                "value": "AEDT"
              },
              "kind": "init"
            },
            {
              "type": "Property",
              "key": {
                "type": "Literal",
                "value": "ACDT"
              },
              "value": {
                "type": "Literal",
                "value": "ACDT"
              },
              "kind": "init"
            },
            {
              "type": "Property",
              "key": {
                "type": "Literal",
                "value": "AZST"
              },
              "value": {
                "type": "Literal",
                "value": "AZST"
              },
              "kind": "init"
            },
            {
              "type": "Property",
              "key": {
                "type": "Literal",
                "value": "IRDT"
              },
              "value": {
                "type": "Literal",
                "value": "IRDT"
              },
              "kind": "init"
            },
            {
              "type": "Property",
              "key": {
                "type": "Literal",
                "value": "EEST"
              },
              "value": {
                "type": "Literal",
                "value": "EEST"
              },
              "kind": "init"
            },
            {
              "type": "Property",
              "key": {
                "type": "Literal",
                "value": "CEST"
              },
              "value": {
                "type": "Literal",
                "value": "CEST"
              },
              "kind": "init"
            },
            {
              "type": "Property",
              "key": {
                "type": "Literal",
                "value": "BST"
              },
              "value": {
                "type": "Literal",
                "value": "BST"
              },
              "kind": "init"
            },
            {
              "type": "Property",
              "key": {
                "type": "Literal",
                "value": "PMDT"
              },
              "value": {
                "type": "Literal",
                "value": "PMDT"
              },
              "kind": "init"
            },
            {
              "type": "Property",
              "key": {
                "type": "Literal",
                "value": "ADT"
              },
              "value": {
                "type": "Literal",
                "value": "ADT"
              },
              "kind": "init"
            },
            {
              "type": "Property",
              "key": {
                "type": "Literal",
                "value": "NDT"
              },
              "value": {
                "type": "Literal",
                "value": "NDT"
              },
              "kind": "init"
            },
            {
              "type": "Property",
              "key": {
                "type": "Literal",
                "value": "EDT"
              },
              "value": {
                "type": "Literal",
                "value": "EDT"
              },
              "kind": "init"
            },
            {
              "type": "Property",
              "key": {
                "type": "Literal",
                "value": "CDT"
              },
              "value": {
                "type": "Literal",
                "value": "CDT"
              },
              "kind": "init"
            },
            {
              "type": "Property",
              "key": {
                "type": "Literal",
                "value": "MDT"
              },
              "value": {
                "type": "Literal",
                "value": "MDT"
              },
              "kind": "init"
            },
            {
              "type": "Property",
              "key": {
                "type": "Literal",
                "value": "PDT"
              },
              "value": {
                "type": "Literal",
                "value": "PDT"
              },
              "kind": "init"
            },
            {
              "type": "Property",
              "key": {
                "type": "Literal",
                "value": "AKDT"
              },
              "value": {
                "type": "Literal",
                "value": "AKDT"
              },
              "kind": "init"
            },
            {
              "type": "Property",
              "key": {
                "type": "Literal",
                "value": "HADT"
              },
              "value": {
                "type": "Literal",
                "value": "HADT"
              },
              "kind": "init"
            }
          ]
        }
      }
    },
    {
      "type": "ExpressionStatement",
      "expression": {
        "type": "AssignmentExpression",
        "operator": "=",
        "left": {
          "type": "MemberExpression",
          "computed": false,
          "object": {
            "type": "MemberExpression",
            "computed": false,
            "object": {
              "type": "Identifier",
              "name": "Date"
            },
            "property": {
              "type": "Identifier",
              "name": "CultureStrings"
            }
          },
          "property": {
            "type": "Identifier",
            "name": "lang"
          }
        },
        "right": {
          "type": "Literal",
          "value": "es-EC"
        }
      }
    }
  ]
}